script.py
securejsonvault-0.1.0.dist-info/LICENSE
securejsonvault-0.1.0.dist-info/METADATA
securejsonvault-0.1.0.dist-info/WHEEL
securejsonvault-0.1.0.dist-info/entry_points.txt
securejsonvault-0.1.0.dist-info/top_level.txt
securejsonvault-0.1.0.dist-info/RECORD
