Metadata-Version: 2.1
Name: securejsonvault
Version: 0.1.0
Summary: A simple Python command-line script to securely manage secrets in a JSON keystore file.
Home-page: https://github.com/I-Need-C8H10N4O2/SecureJSONVault
Author: Karam T.
Author-email: dev@tayyem.eu
License: GPLv3
Classifier: Programming Language :: Python :: 3
Classifier: License :: OSI Approved :: GNU General Public License v3 (GPLv3)
Classifier: Operating System :: OS Independent
Classifier: Operating System :: Microsoft :: Windows
Classifier: Operating System :: POSIX :: Linux
Requires-Python: >=3.10
License-File: LICENSE
Requires-Dist: click ==8.1.7
Requires-Dist: cryptography ==42.0.7
Requires-Dist: jinja2 ==3.1.4
